disp/__init__.py
disp/spark.py
disp-0.0.2.dist-info/DESCRIPTION.rst
disp-0.0.2.dist-info/METADATA
disp-0.0.2.dist-info/RECORD
disp-0.0.2.dist-info/WHEEL
disp-0.0.2.dist-info/metadata.json
disp-0.0.2.dist-info/top_level.txt
